pz/__init__.py
pz/config.py
pz/main.py
pz/pz.py
ezpz4u-0.0.3.dist-info/METADATA
ezpz4u-0.0.3.dist-info/WHEEL
ezpz4u-0.0.3.dist-info/entry_points.txt
ezpz4u-0.0.3.dist-info/top_level.txt
ezpz4u-0.0.3.dist-info/RECORD
